data_summary/__init__.py
data_summary/catalog/__init__.py
data_summary/summary/__init__.py
data_summary/summary/df.py
data_summary/viz/__init__.py
pandas_summary/__init__.py
data_summary-0.1.0.dist-info/LICENSE
data_summary-0.1.0.dist-info/METADATA
data_summary-0.1.0.dist-info/WHEEL
data_summary-0.1.0.dist-info/top_level.txt
data_summary-0.1.0.dist-info/RECORD
